owlspec/__init__.py
owlspec/emission_line.py
owlspec/spectrum.py
owlspec/util.py
owlspec/emitter/__init__.py
owlspec/emitter/level.py
owlspec/emitter/species.py
owlspec/emitter/transition.py
owlspec/nist_levels/__init__.py
owlspec/nist_levels/core.py
owlspec/stark/__init__.py
owlspec/stark/gigosos_he_loader.py
owlspec/stark/gigosos_loader.py
owlspec/stark/griem.py
owlspec/stark/stark.py
owlspec/vdW/__init__.py
owlspec/vdW/vdW.py
owlspec-0.3.4.dist-info/licenses/LICENSE
owlspec-0.3.4.dist-info/METADATA
owlspec-0.3.4.dist-info/WHEEL
owlspec-0.3.4.dist-info/top_level.txt
owlspec-0.3.4.dist-info/RECORD
