Metadata-Version: 2.4
Name: owlspec
Version: 0.3.4
Summary: Library for optical emission spectroscopy of low-temperature plasmas.
Home-page: https://github.com/mimurrayy/owl
Author: Julian Held
Author-email: j.held@tue.nl
License: MIT
Platform: any
Classifier: Programming Language :: Python :: 3
Classifier: License :: OSI Approved :: MIT License
Classifier: Operating System :: OS Independent
Requires-Python: >=3.8.1
License-File: LICENSE
Requires-Dist: numpy>=1.19.5
Requires-Dist: scipy>=1.6.0
Requires-Dist: mendeleev>=0.13.0
Requires-Dist: astroquery>=0.4.5
Requires-Dist: roman>=2.0
Requires-Dist: platformdirs>=2.6.0
Requires-Dist: pyplas>=0.2.1
Dynamic: author
Dynamic: author-email
Dynamic: classifier
Dynamic: description
Dynamic: description-content-type
Dynamic: home-page
Dynamic: license
Dynamic: license-file
Dynamic: platform
Dynamic: requires-dist
Dynamic: requires-python
Dynamic: summary
